__init__.py
central_set_cli.py
central_set_cli-1.0.1.dist-info/LICENSE
central_set_cli-1.0.1.dist-info/METADATA
central_set_cli-1.0.1.dist-info/WHEEL
central_set_cli-1.0.1.dist-info/top_level.txt
central_set_cli-1.0.1.dist-info/RECORD
